pdfner/__init__.py
pdfner/document.py
pdfner/io.py
pdfner/pdf.py
pdfner/nlp/__init__.py
pdfner/nlp/base.py
pdfner/nlp/corenlp.py
pdfner/nlp/spacy.py
pdfner/tests/__init__.py
pdfner/tests/conftest.py
pdfner/tests/test_api.py
pdfner/tests/test_json_serde.py
pdfner-0.1.1.dist-info/LICENSE
pdfner-0.1.1.dist-info/METADATA
pdfner-0.1.1.dist-info/WHEEL
pdfner-0.1.1.dist-info/top_level.txt
pdfner-0.1.1.dist-info/RECORD
