Metadata-Version: 2.1
Name: pdfner
Version: 0.1.1
Summary: Information extraction and named-entity recognition for indexing PDFs
Home-page: https://github.com/hnluu8/pdfner
Author: Hung Luu
Author-email: hung.luu@outlook.com
License: MIT
Keywords: pdf, ner
Platform: UNKNOWN
Classifier: Development Status :: 4 - Beta
Classifier: Intended Audience :: Science/Research
Classifier: Programming Language :: Python
Classifier: Programming Language :: Python :: 3
Classifier: Programming Language :: Python :: 3.6
Classifier: Programming Language :: Python :: 3.7
Requires-Python: <3.8,>=3.6
Requires-Dist: dask[delayed] (==2.9.0)
Requires-Dist: simplejson (==3.17.0)
Requires-Dist: pdf2image (==1.4.2)
Requires-Dist: pymupdf (==1.16.8)
Requires-Dist: pikepdf (==1.1.0)
Requires-Dist: img2pdf (==0.3.3)
Requires-Dist: textacy (==0.6.2)
Requires-Dist: msgpack-python (==0.5.6)
Requires-Dist: pynlp (==0.4.2)
Provides-Extra: test
Requires-Dist: pytest (>=5.0.0) ; extra == 'test'
Requires-Dist: pytest-cov ; extra == 'test'
